{
  "alternate_link": {
    "alternate_type": "legacy",
    "aonid": 356,
    "game-obj": "Feats",
    "type": "alternate_link"
  },
  "aonid": 4769,
  "edition": "remastered",
  "feat": {
    "action_type": {
      "name": "Two Actions",
      "subtype": "action_type",
      "type": "stat_block_section"
    },
    "level": 1,
    "name": "Double Slice",
    "requirement": "You are wielding two melee weapons, each in a different hand",
    "subtype": "feat",
    "text": "You lash out at your foe with both weapons. Make two Strikes, one with each of your two melee weapons, each using your current multiple attack penalty. Both Strikes must have the same target. If the second Strike is made with a weapon that doesn\u2019t have the agile trait, it takes a \u20132 penalty.  \n  \nIf both attacks hit, combine their damage, and then add any other applicable effects from both weapons. You add any precision damage only once, to the attack of your choice. Combine the damage from both Strikes and apply resistances and weaknesses only once. This counts as two attacks when calculating your multiple attack penalty.",
    "traits": [
      {
        "alternate_link": {
          "alternate_type": "legacy",
          "aonid": 71,
          "game-obj": "Traits",
          "type": "alternate_link"
        },
        "edition": "remastered",
        "game-id": "6ebf425077bbbddac495f52d250988dc",
        "game-obj": "Traits",
        "name": "Fighter",
        "sources": [
          {
            "errata": {
              "alt": "2.0",
              "aonid": 216,
              "game-obj": "Sources",
              "name": "2.0",
              "type": "link"
            },
            "link": {
              "alt": "Player Core pg. 456",
              "aonid": 216,
              "game-obj": "Sources",
              "name": "Player Core pg. 456",
              "type": "link"
            },
            "name": "Player Core",
            "page": 456,
            "type": "source"
          }
        ],
        "text": "This indicates abilities from the fighter class.",
        "type": "trait"
      }
    ],
    "type": "stat_block_section"
  },
  "game-id": "e7bbdc63feb82d1e3814de6f0f2f36e1",
  "game-obj": "Feats",
  "license": {
    "license": "Open RPG Creative license",
    "name": "ORC Notice",
    "sections": [
      {
        "name": "Attribution",
        "sections": [
          {
            "name": "Player Core",
            "text": "***Pathfinder Player Core*** \u00a9 2023 Paizo Inc., Designed by Logan Bonner, Jason Bulmahn, Stephen Radney-MacFarland, and Mark Seifter. Authors: Alexander Augunas, Kate Baker, Logan Bonner, Jason Bulmahn, Carlos Cabrera, Calder CaDavid, James Case, Eleanor Ferron, Steven Hammond, Joan Hong, Vanessa Hoskins, James Jacobs, Jenny Jarzabski, Erik Keith, Dustin Knight, Lyz Liddell, Luis Loza, Patchen Mortimer, Dennis Muldoon, Stephen Radney-MacFarland, Mikhail Rekun, David N. Ross, Michael Sayre, Mark Seifter, Kendra Leigh Speedling, Mark Thompson, Clark Valentine, Andrew White, Landon Winkler, and Linda Zayas-Palmer",
            "type": "section"
          }
        ],
        "text": "This product is based on the following Licensed Material:",
        "type": "section"
      },
      {
        "name": "Attributing us",
        "sections": [
          {
            "name": "Pathfinder Open Reference",
            "text": "\u00a9 2023 Masterwork Tools LLC, Authors: Devon Jones, Monica Jones.",
            "type": "section"
          }
        ],
        "text": "If you use our Licensed Material in your own published works, please credit us as follows:",
        "type": "section"
      },
      {
        "name": "Reserved Material",
        "text": "Reserved Material elements in this product include, but may not be limited to: [none]",
        "type": "section"
      },
      {
        "name": "Expressly Designated Licensed Material",
        "text": "The following elements are owned by the Licensor and would otherwise constitute Reserved Material and are hereby designated as Licensed Material: [None].",
        "type": "section"
      }
    ],
    "subtype": "license",
    "text": "This product is licensed under the ORC License to be held in the Library of Congress and available online at various locations including paizo.com/orclicense, azoralaw.com/orclicense, and others. All warranties are disclaimed as set forth therein.",
    "type": "section"
  },
  "name": "Double Slice",
  "pfs": {
    "availability": "Standard",
    "subtype": "pfs",
    "type": "stat_block_section"
  },
  "schema_version": 1.0,
  "sections": [
    {
      "links": [
        {
          "alt": "Graceful Poise",
          "aonid": 4848,
          "game-obj": "Feats",
          "name": "Graceful Poise",
          "type": "link"
        }
      ],
      "name": "Double Slice Leads To...",
      "sources": [
        {
          "errata": {
            "alt": "2.0",
            "aonid": 216,
            "game-obj": "Sources",
            "name": "2.0",
            "type": "link"
          },
          "link": {
            "alt": "Player Core pg. 140",
            "aonid": 216,
            "game-obj": "Sources",
            "name": "Player Core pg. 140",
            "type": "link"
          },
          "name": "Player Core",
          "page": 140,
          "type": "source"
        }
      ],
      "text": "*Graceful Poise*",
      "type": "section"
    }
  ],
  "sources": [
    {
      "errata": {
        "alt": "2.0",
        "aonid": 216,
        "game-obj": "Sources",
        "name": "2.0",
        "type": "link"
      },
      "link": {
        "alt": "Player Core pg. 140",
        "aonid": 216,
        "game-obj": "Sources",
        "name": "Player Core pg. 140",
        "type": "link"
      },
      "name": "Player Core",
      "page": 140,
      "type": "source"
    }
  ],
  "type": "feat"
}