{
  "aonid": 224,
  "edition": "remastered",
  "game-id": "e8bd76985b7a40833e81923267451e73",
  "game-obj": "Sources",
  "license": {
    "license": "Open RPG Creative license",
    "name": "ORC Notice",
    "sections": [
      {
        "name": "Attribution",
        "sections": [
          {
            "name": "Pathfinder #198: No Breath to Cry",
            "text": "<div> <i><b>Pathfinder Core Rulebook (Second Edition)</b></i> \u00a9 2019, Paizo Inc.; Authors: Logan Bonner, Jason Bulmahn, Stephen Radney-MacFarland, and Mark Seifter.<br/> <i><b>Pathfinder Adventure Path #198: No Breath to Cry</b></i> \u00a9 2023, Paizo Inc.; Authors: Dan Cascone and Eleanor Ferron, with Jeremy Blum, Dana Ebert, Joshua Kim, and Michelle Kim    </div>",
            "type": "section"
          }
        ],
        "text": "This product is based on the following Licensed Material:",
        "type": "section"
      },
      {
        "name": "Attributing us",
        "sections": [
          {
            "name": "Pathfinder Open Reference",
            "text": "\u00a9 2023 Masterwork Tools LLC, Authors: Devon Jones, Monica Jones.",
            "type": "section"
          }
        ],
        "text": "If you use our Licensed Material in your own published works, please credit us as follows:",
        "type": "section"
      },
      {
        "name": "Reserved Material",
        "text": "Reserved Material elements in this product include, but may not be limited to: [none]",
        "type": "section"
      },
      {
        "name": "Expressly Designated Licensed Material",
        "text": "The following elements are owned by the Licensor and would otherwise constitute Reserved Material and are hereby designated as Licensed Material: [None].",
        "type": "section"
      }
    ],
    "subtype": "license",
    "text": "This product is licensed under the ORC License to be held in the Library of Congress and available online at various locations including paizo.com/orclicense, azoralaw.com/orclicense, and others. All warranties are disclaimed as set forth therein.",
    "type": "section"
  },
  "name": "Pathfinder #198: No Breath to Cry",
  "product_line": "Adventure Paths",
  "release_date": "2023-12-25",
  "schema_version": 1.0,
  "type": "source"
}