{
    "name": "Grasping Earth",
    "type": "spell",
    "sources": [
        {
            "type": "source",
            "name": "Rage of Elements",
            "link": {
                "type": "link",
                "name": "Rage of Elements pg. 95",
                "alt": "Rage of Elements pg. 95",
                "game-obj": "Sources",
                "aonid": 205
            },
            "page": 95,
            "errata": {
                "type": "link",
                "name": "2.0",
                "alt": "2.0",
                "game-obj": "Sources",
                "aonid": 205
            }
        }
    ],
    "aonid": 1334,
    "game-obj": "Spells",
    "spell": {
        "name": "Grasping Earth",
        "type": "stat_block_section",
        "subtype": "spell",
        "action_type": {
            "type": "stat_block_section",
            "subtype": "action_type",
            "name": "Two Actions"
        },
        "traits": [
            {
                "type": "stat_block_section",
                "subtype": "trait",
                "name": "Concentrate",
                "link": {
                    "type": "link",
                    "name": "Concentrate",
                    "alt": "Concentrate",
                    "game-obj": "Traits",
                    "aonid": 32
                }
            },
            {
                "type": "stat_block_section",
                "subtype": "trait",
                "name": "Earth",
                "link": {
                    "type": "link",
                    "name": "Earth",
                    "alt": "Earth",
                    "game-obj": "Traits",
                    "aonid": 55
                }
            },
            {
                "type": "stat_block_section",
                "subtype": "trait",
                "name": "Manipulate",
                "link": {
                    "type": "link",
                    "name": "Manipulate",
                    "alt": "Manipulate",
                    "game-obj": "Traits",
                    "aonid": 104
                }
            }
        ],
        "traditions": "arcane, primal",
        "range": "60  feet",
        "area": "10-foot burst on the ground",
        "defense": "Fortitude",
        "duration": "sustained up to 1 minute",
        "heightened": [
            {
                "type": "stat_block_section",
                "subtype": "heightened",
                "increment": 2,
                "text": "The bludgeoning damage dealt when you Sustain this spell increases by 1d6 for grabbed creatures and 2d6 for restrained creatures."
            }
        ],
        "success": "The creature is unaffected.",
        "failure": "The creature is grabbed by the earth.",
        "critical_failure": "The creature is restrained by the earth."
    },
    "game-id": "07caba1ff1f3a60e8c785e1c98021c48",
    "spell_type": "spell",
    "rank": 4,
    "text": "Handlike protrusions of rock and soil grab and bury creatures. Each creature in the area when you cast the spell, and each creature that ends its turn in the area during the spell's duration, must attempt a Fortitude save. The first time each round you Sustain this spell, each creature still grabbed by the earth takes 1d6 bludgeoning damage, and each creature restrained by the earth takes 2d6 bludgeoning damage. A creature can attempt to Escape, rolling against your spell DC.",
    "links": [
        {
            "type": "link",
            "name": "grabbed",
            "alt": "grabbed",
            "game-obj": "Conditions",
            "aonid": 20
        },
        {
            "type": "link",
            "name": "restrained",
            "alt": "restrained",
            "game-obj": "Conditions",
            "aonid": 33
        },
        {
            "type": "link",
            "name": "Escape",
            "alt": "Escape",
            "game-obj": "Actions",
            "aonid": 79
        },
        {
            "type": "link",
            "name": "arcane",
            "alt": "arcane",
            "href": "Spells.aspx?Tradition=1"
        },
        {
            "type": "link",
            "name": "primal",
            "alt": "primal",
            "href": "Spells.aspx?Tradition=4"
        }
    ],
    "edition": "remastered",
    "license": {
        "name": "ORC Notice",
        "type": "section",
        "sections": [
            {
                "name": "Attribution",
                "type": "section",
                "text": "This product is based on the following Licensed Material:",
                "sections": [
                    {
                        "name": "Rage of Elements",
                        "type": "section",
                        "text": "***Pathfinder Core Rulebook (Second Edition)*** \u00a9 2019, Paizo Inc.; Authors: Logan Bonner, Jason Bulmahn, Stephen Radney-MacFarland, and Mark Seifter.  \n ***Pathfinder Rage of Elements*** \u00a9 2023, Paizo Inc.; Authors: Logan Bonner, Jason Bulmahn, James Case, Jessica Catalan, Andrew D. Geels, Sen H.H.S., Patrick Hurley, Jason Keeley, Luis Loza, Mark Moreland, Jonathan Morgantini, AJ Neuro, Jessica Redekop, Solomon St. John, Michael Sayre, Mark Seifter, Shahreena Shahrani, Shay Snow, Levi Steadman, Mari Tokuda, Ruvaid Virk, Andrew White, and Linda Zayas-Palmer."
                    }
                ]
            },
            {
                "name": "Attributing us",
                "type": "section",
                "text": "If you use our Licensed Material in your own published works, please credit us as follows:",
                "sections": [
                    {
                        "name": "Pathfinder Open Reference",
                        "type": "section",
                        "text": "\u00a9 2023 Masterwork Tools LLC, Authors: Devon Jones, Monica Jones."
                    }
                ]
            },
            {
                "name": "Reserved Material",
                "type": "section",
                "text": "Reserved Material elements in this product include, but may not be limited to: [none]"
            },
            {
                "name": "Expressly Designated Licensed Material",
                "type": "section",
                "text": "The following elements are owned by the Licensor and would otherwise constitute Reserved Material and are hereby designated as Licensed Material: [None]."
            }
        ],
        "subtype": "license",
        "license": "Open RPG Creative license",
        "text": "This product is licensed under the ORC License to be held in the Library of Congress and available online at various locations including paizo.com/orclicense, azoralaw.com/orclicense, and others. All warranties are disclaimed as set forth therein."
    },
    "schema_version": 1.0
}